calculadora/__init__.py
calculadora/operacoes.py
minha_calculadora-0.1.0.dist-info/METADATA
minha_calculadora-0.1.0.dist-info/WHEEL
minha_calculadora-0.1.0.dist-info/top_level.txt
minha_calculadora-0.1.0.dist-info/RECORD
